setup.py
function_adding/__init__.py
function_adding/add_no_sample.py
function_adding_only.egg-info/PKG-INFO
function_adding_only.egg-info/SOURCES.txt
function_adding_only.egg-info/dependency_links.txt
function_adding_only.egg-info/top_level.txt